flask_crontab.py
flask_crontab-0.1.2.dist-info/LICENSE
flask_crontab-0.1.2.dist-info/METADATA
flask_crontab-0.1.2.dist-info/WHEEL
flask_crontab-0.1.2.dist-info/entry_points.txt
flask_crontab-0.1.2.dist-info/top_level.txt
flask_crontab-0.1.2.dist-info/RECORD
