Metadata-Version: 2.1
Name: flask-crontab
Version: 0.1.2
Summary: Simple Flask scheduled tasks without extra daemons
Home-page: https://github.com/frostming/flask-crontab
Author: frostming
Author-email: mianghong@gmail.com
License: MIT
Platform: UNKNOWN
Classifier: License :: OSI Approved :: MIT License
Classifier: Programming Language :: Python
Classifier: Programming Language :: Python :: 3.5
Classifier: Programming Language :: Python :: 3.6
Classifier: Programming Language :: Python :: 3.7
Classifier: Programming Language :: Python :: 3.8
Classifier: Programming Language :: Python :: Implementation :: CPython
Classifier: Programming Language :: Python :: Implementation :: PyPy
Requires-Python: >=3.5
